Workbook

Sheet Summary
B1: Roof Extension and | F1: Revision | G1: 0
B2: Refurbishment of Three Flats | F2: Date | G2: =NOW() -> 43621.606 | H2: RATE BUILD UP
B3: 95 Malvern Road London NW6 5PU | H3: Labour | I3: Minimum wage is £7.20/hr | W3: Materials | AN3: Plant/Consumables | AQ3: Large plant items price in prelims | AW3: Overheads | AY3: Profit | BA3: Total Rate | BC3: Comments
D4: Quant | E4: unit | F4: Rate | G4: Add/omit | AQ4: Spread across total rates
B5: Summary page | D5: C | E5: D | F5: E | G5: F
A6: Item | B6: Collection | C6: £ | H6: Labour Type 1 | I6: Labour Rate £/Hr | J6: Time per rate | K6: Gang Number | L6: Labour Type 2 | M6: Labour Rate £/Hr | N6: Time per rate | O6: Gang Number | P6: Labour Constant | Q6: Unit Of Measure | R6: NPO | S6: Distribute allowance | T6: Uplift for constraints | U6: Total Labour | W6: MAT 1 | X6: Unit Of Measure | Y6: Cost per unit | Z6: Quant | AA6: MAT 2 | AB6: Unit Of Measure | AC6: Cost per unit | AD6: Quant | AE6: MAT 3 | AF6: Unit Of Measure | AG6: Cost per unit | AH6: Quant | AI6: Waste | AJ6: Deliveries | AK6: Waste disposal | AL6: Total Mats Rate | AN6: Plant item | AO6: Number of items | AP6: Buy/Hire ? | AQ6: Cost per unit | AR6: Deliveries | AS6: Maintainance | AT6: Insurance | AU6: Total | AW6: 0.05 | AY6: 0.15
A9: A | B9: Preliminaries | C9: =Prelims!H87 -> 29508
B11: Full external scaffold @ 2m lifts - provisional sum | C11: 17500
B13: Specifications
B14: Schedule of works | C14: =Schedule!C107 -> 12500
B15: 2.0 Enabling works
B16: 2.1 Asbestos | C16: =Schedule!C115 -> 5700
B17: 3.0 Site set up | C17: Inc
A19: B | B19: BUTTERFLY ROOF
B21: 4.0 ROOF EXTENSION | C21: =Schedule!C228 -> 53564
B22: 5.0 Rainwater Goods | C22: =Schedule!C235 -> 1081
B23: 6.0 Surface water drains - provisional | C23: =Schedule!C244 -> 2200
A25: C | B25: EXISTING ELEVATIONS
B27: 7.0 Cleaning brickwork | C27: =Schedule!C251 -> 720
B28: 8.0 Brickwork repairs | C28: =Schedule!C262 -> 3300
B29: 9.0 Rear flat roofs | C29: =Schedule!C267 -> 2000
B30: 10.0 Windows | C30: =Schedule!C290 -> 18484
B31: 11.0 External door | C31: =Schedule!C295 -> 500
B32: 12.0 Landscape | C32: =Schedule!C303 -> 13750
B33: 13.0 External Decorations | C33: =Schedule!C314 -> 4120
B34: 14.0 Cleaning | C34: =Schedule!C319 -> Inc
A36: D | B36: INTERNAL REFURBISHMENT
B38: 15.0 Demolition/ Strip out | C38: =Schedule!C353 -> 6170
B39: 16.0 Structural works | C39: =Schedule!C378 -> 19643.762
B40: 17.0 Stairs | C40: =Schedule!C394 -> 16084
B41: 18.0 Walls | C41: =Schedule!C436 -> 25936
B42: 19.0 Plaster skim coat | C42: =Schedule!C444 -> 8260
B43: 20.0 New Kitchens | C43: =Schedule!C460 -> 32784
B44: 21.0 Bathrooms | C44: =Schedule!C474 -> 18860
B45: 22.0 Internal Joinery | C45: =Schedule!C489 -> 14036
B46: 23.0 Floor finishes | C46: =Schedule!C510 -> 13923
B47: 24.0 Internal Decorations | C47: =Schedule!C522 -> 10876
B48: 25.0 Window blinds | C48: =Schedule!C527 -> 3020
B50: 26.0 MECHANICAL, ELECTRICAL, WATER DISTRIBUTION & DRAINAGE
B52: 27.0 Utility Supplies | C52: Excluded
B53: 28.0 Electrical Installations | C53: =Schedule!C634 -> 28010
B54: 29.0 Gas supply | C54: =Schedule!C639 -> 1890
B55: 30.0 Central Heating | C55: =Schedule!C651 -> 16520
B56: 31.0 Cold water distribution | C56: =Schedule!C665 -> 1222
B57: 32.0 Hot water distribution | C57: Inc
B58: 33.0 Drainage | C58: =Schedule!C693 -> 4546
B59: 34.0 Builders work in connection services. | C59: Inc
B60: 35.0 Under ground drains | C60: =Schedule!C705 -> 1000
B61: 36.0 Cleaning | C61: Inc
B63: 37.0 Contingency £15,000 | C63: 15000
B65: TOTAL CONTRACT SUM | C65: =SUM(C9:C63) -> 402707.76 | E65: =Schedule!C723 -> 696399.52 | F65: =E65-C65 -> 293691.76
A67: Exclusions and Clarifications
A68: We have not allowed to upgrade the existing utility incoming supplies. You may want to do this before works begin.
A69: We assume any party wall awards will be granted before we commence works. We do not take responsibility of the condition of existing structures or dealing with 3rd party walls
A70: We exclude any design responsibility for these works.
A71: We require a lead in to commence on site of 6 weeks. This excludes any third party approvals.
A72: We have allowed for the works to be completed in one continuous visit
A73: All provisional sums included are client provisional sums
A74: We require payment every 2 weeks. We will submit valuation every 2 weeks. We request 0% retention is held on every payment. Price excludes VAT
A75: Any changes to the agreed works made by the client may result in additional costs

Sheet Schedule
B1: Roof Extension and | G1: Revision | H1: 0
B2: Refurbishment of Three Flats | G2: Date | H2: =NOW() -> 43621.606 | I2: RATE BUILD UP
B3: 95 Malvern Road London NW6 5PU | I3: Labour | J3: Minimum wage is £7.20/hr | X3: Materials | AO3: Plant/Consumables | AR3: Large plant items price in prelims | AX3: Overheads | AZ3: Profit | BB3: Total Rate | BD3: Comments
E4: Quant | F4: unit | G4: Rate | H4: Add/omit | AR4: Spread across total rates
E5: C | F5: D | G5: E | H5: F
A6: Item | B6: The Works Description | C6: £ | I6: Labour Type 1 | J6: Labour Rate £/Hr | K6: Time per rate | L6: Gang Number | M6: Labour Type 2 | N6: Labour Rate £/Hr | O6: Time per rate | P6: Gang Number | Q6: Labour Constant | R6: Unit Of Measure | S6: NPO | T6: Distribute allowance | U6: Uplift for constraints | V6: Total Labour | X6: MAT 1 | Y6: Unit Of Measure | Z6: Cost per unit | AA6: Quant | AB6: MAT 2 | AC6: Unit Of Measure | AD6: Cost per unit | AE6: Quant | AF6: MAT 3 | AG6: Unit Of Measure | AH6: Cost per unit | AI6: Quant | AJ6: Waste | AK6: Deliveries | AL6: Waste disposal | AM6: Total Mats Rate | AO6: Plant item | AP6: Number of items | AQ6: Buy/Hire ? | AR6: Cost per unit | AS6: Deliveries | AT6: Maintainance | AU6: Insurance | AV6: Total | AX6: 0.05 | AZ6: 0.15
A7: 1 | B7: SECTION THREE – SCHEDULE OF WORKS
A8: 1.1 | B8: Scope of Works
B9: The project involves internal refurbishment and roof extension of the existing property from ground to 2nd floor level. The lower ground floor is under separate ownership and excluded from the works. The contractor is to make allowance for the neighbouring properties being fully occupied during the course of the works. | C9: No allowance for LGF made (internal and external)
A11: 1.2 | B11: General Items
B12: This specification describes the requirements, but all the works implied thereby or necessary for the full and proper completion of the Contract is to be performed by the Contractor in the best and most suitable manner even if not particularly referred to herein.
B14: The Contractor should note that all items of work contained within this schedule have been described in reasonable detail, but the Contractor shall consider them in conjunction with manufacturers recommendations and actual work on site and shall include in his price for everything necessary to allow him to carry out the works in the best manner, whether specifically mentioned or not.
B16: The contractor is to ensure all areas are appropriately secured to prevent access by unauthorised persons for the duration of the contract. The contractor shall provide and locate all welfare facilities and storage compound as required but will ensure written consent from the Local Authority and CA is obtained prior to installation on site.
B18: The contractor will provide all materials, plant, labour and expertise necessary to facilitate the successful completion of the works. All materials are to be as specified and used in accordance with all good codes of practice and the manufacturer’s recommendations and instructions.
A20: 1.3 | B20: Site Rules
B21: Note: The following provisions are expressly made: -
B22: a. Site rules are primarily to be developed by the Contractor. The Contractor is to ensure that all site operatives are fully aware of the site rules.
B23: b. Operational hours are from 0800hrs to 1730hrs Monday to Friday
B24: c. The Contractor is to ensure that general rubbish does not accumulate on the site and shall make arrangements for its proper disposal off-site. Compliance with the Control of Asbestos Regulations should be ensured when disposing of any Asbestos Containing Materials. | C24: Asbestos dealt with under below provisional sum
B25: d. The Contractor should take all necessary precautions to prevent nuisance from noise, smoke, dust, rubbish and any other causes
B26: e. All Contractors employees must be signed in and out on a daily basis as part of the Contract requirements.
B27: f. Radios, tape players and CD players will not be permitted on site without the express permission of the CA.
B28: g. Smoking will not be permitted on site.
B29: h. Bonfires or burning of materials and rubbish will not be permitted
B30: i. At no point are materials to be stored on neighbouring properties or unlicensed areas.
B32: The Contractor is to protect against damage of all features and structures including neighbouring buildings, fences, footpaths, trees etc. The contractor is responsible for making good any damage caused on completion.
A34: 1.4 | B34: Temporary Services
B35: The Contractor may use the electrical and water supplies currently available on site during the Contract.
B37: The Contractor must indemnify the Employer against damage and misuse of the power and water supplies.
A39: 1.5 | B39: Person in Charge
B40: The contractor is to have a designated site foreman in charge on site to act as a point of contact for all site visitors throughout the project. The person in charge shall not be changed without the permission of the CA, such consent will not to be unreasonably withheld.
A42: 1.6 | B42: Health & Safety
B43: The Contractor will also be responsible for all aspects of health and safety on the site and the immediate surrounding areas.
B45: The Contractor shall take all necessary precautions to ensure that the works are carried out in a safe manner in accordance with their obligations under the Health and Safety at Work Act 1974 and any subsequent Regulations and Rules enacted under this Act.
B47: The Contractor shall take all necessary steps to secure the site, or plant, machinery and tools against misuse by unauthorised persons particularly out of working hours.
B49: The Contractor is to check the fire evacuation procedures to the existing site/buildings and ensure all fire escape routes are clear at all times.
B51: The Contractor is to allow for the provision of all necessary safety equipment to comply with all relevant Health and Safety Regulations. Correct PPE is to be worn at all times and operatives found not wearing such equipment will be asked to leave site by the Contract Administrator.
B53: The contractor shall at all times apply the general principles embodied in the Current Construction (Design & Management) Regulations 2015.
B55: The works will be notifiable and the contractor shall allow for compliance with the Pre-Construction Information Pack and provision of information necessary for the Construction Phase Health and Safety plan. The contractor shall also allow for providing all information necessary and supplying this to the Principal Designer for inclusion in the file. Allow for keeping a daily site diary and weekly photographs.
B57: The contractor should also report any observed defects or otherwise in the construction and services of the sites that may constitute a hazard.
B59: Users of special substances should also be aware of and apply the advice contained in COSHH notes.
A61: 1.7 | B61: Storage
B62: No liability will be accepted for loss or damage to any materials or equipment stored on site. The exact location of site storage and welfare facilities provided by the contractor is to be agreed at the pre-contract meeting.
A64: 1.8 | B64: Access
B65: Safe access and protection must be afforded at all times by way of scaffolding or otherwise in accordance with all relevant health & safety legislation.
B67: The contractor may erect scaffold, temporary towers, ladders, hoists, cranes, protective hoardings, clear sheeting, handrails, etc. to form all necessary working platforms that are required to ensure that all works can be carried out in a safe and workmanlike manner and in accordance with the work at height regulations 2005. The contractor shall allow for compliance with all Scaffolding Regulations, including local authority licences, agreement with neighbours and providing a fully boarded and protected scaffold when erected. The scaffold is to be arranged so the public and occupiers of the property can pass along the pavement and into entrances at ground floor level without restriction and that all access and egress points are maintained and that the fire escape routes are kept clear. Protection to the scaffold shall include all necessary boards and fans to protect all such routes and access ways from any falling materials. Monoflex sheeting is to be fitted to all external elevations of the scaffold. | C67: External scaffold included on summary sheet are provisional sum
B69: At ground floor level allow for painting all standards white and providing illumination in the hours of darkness in accordance with the Local Authorities recommendations. Include for all necessary spreader boards at the feet of all standards. Confirm with the CA instructions in case of bearing scaffold onto areas of the building above ground floor level. The contractor is to allow for all necessary handrails, perimeter lighting and also plant, tools, tackle and other equipment to comply with statutory recommendations and local authority regulations. Allow for providing all necessary ladders, safety, and security to access all working areas. Out of hours and during public holidays and other periods when scaffold is not in use, including at night and at weekends, the contractor shall remove the bottom ladders and secure to prevent unauthorised access.
B71: Contractor to procure any specialist engineering for scaffold at the contractors cost.
B73: The contractor shall include for installing an intruder alarm system to the bottom lift of the scaffolding so that it is fully protected when the scaffold is not being worked upon. Allow for installing floodlights to be linked to an infra- red intruder alarm system providing 24 hour monitoring linked to an alarm panel. The alarm must be allowed for detecting out of hours unauthorised access to all zones of the scaffold. The system must be either Permanex or UBX or other similar approved. The contractor shall allow for making the alarm as false alarm free as possible. The alarm will be installed and working once the first lift of scaffolding is erected and even before the lift is boarded or completed, and will not be removed until the bottom lift is to be removed. The contractor shall allow for all necessary alterations to the alarm system
B75: The contractor is responsible for arranging and payment of all scaffold licences and ensuring that they are in place before works commence. All licences to last the entire duration of the contract.
B77: The contractor is to arrange and pay for any necessary road/ pavement closures and obtain the licences and provide them to the C.A in the event of a request.
B79: The contractor to allow to inspect all scaffolding at weekly intervals, or after inclement weather, with competent and authorised scaffolder or suitably trained supervisor, to ensure scaffold is stable and secure, for contract duration. Certificate to be issued to the contractor that scaffolding is stable and secure and to be sent to CA on day of issue.
B81: All scaffold fixing points to the building must be made good following completion of the work to the complete satisfaction of the CA.
A83: PS | B83: Contractor to provide all materials, labour and expertise to provisionally erect a temporary roof to cover 95 Malvern Road, London, NW6 5PU completely while the roof works are undertaken. | C83: 12500
A85: 1.9 | B85: Cleaning
B86: On a daily bases, contractor to ensure that all areas of the site, pavement and road are kept free from dirt and debris and cleaned at least once a day.
B88: On completion of the works, clean all areas complete leaving clean, tidy and in full working order. Remove all dirt, debris and splashes etc. from all surfaces leaving the area entirely fit for use and to the satisfaction of the CA.
A90: 1.1 | B90: Waste and Debris
B91: The contractor shall allow to remove all rubbish and debris and other arising’s from site as and when necessary and dispose in accordance with any relevant legislation.
B93: Provide all skips, licences and waste facilities as required for the removal of all waste throughout the project. Skips are to be the responsibility of the contractor.
A95: 1.11 | B95: Pricing
B96: Every item in this specification is to be included and indicating a price for that item. Any item not priced will be considered as being included within the tender. It is strongly recommended that the contractor inspects site prior to submitting costs.
A98: 1.12 | B98: Samples
B99: The contractor is to provide samples of all items as requested in the Schedule for approval by the Contract Administrator.
A101: 1.13 | B101: Programme
B102: The contractor shall provide a programme of works to the CA prior to commencement of the project showing all stages and timescales for each work item. The contractors tender price is to remain open and valid for that period of time should he be appointed as the successful Principal Contractor. Allow for a 12 months defect liability period.
A104: 1.14 | B104: Welfare/ site accommodation
B105: The contractor is to provide site accommodation as required in order to undertake the works in a responsible manner in accordance with the Health & Safety Regulations.
B107: Total Carried to Collection Sheet | C107: =SUM(C83:C106) -> 12500 | D107: =C107 -> 12500
A109: 2 | B109: Enabling works
A110: 2.1 | B110: Asbestos
B111: Contractor to allow for undertaking a Refurbishment and Demolition Asbestos Survey prior to the works taking place. Once the results are obtained, a copy is to be sent to the C.A immediately. | C111: 700
B113: P.S allowed to encapsulate/ remove asbestos containing materials. | C113: 5000
B115: Total Carried to Collection Sheet | C115: =SUM(C111:C113) -> 5700 | D115: =C115 -> 5700
A117: 3 | B117: Site set up
B118: Carefully disconnect electric, gas, water and waste supplies as necessary leaving all safe to facilitate the works. | C118: Inc
B120: Provide temporary electrical supply as necessary to facilitate the works. | C120: Inc
B122: Total Carried to Collection Sheet | C122: =SUM(C118:C121) -> 0
A124: 4 | B124: ROOF EXTENSION
A125: 4.1 | B125: Strip out/ demolition
B126: Contractor to carefully remove the existing roof rafters, ridges, roof coverings where shown on drawings including, but not limited to felt, sarking, underlay, slates/ tiles/ asbestos cement sheets, battens, insulation, box gutters, leadwork, flashing, and dispose from site immediately. | C126: =G126 -> 4560 | E126: 80 | F126: m2 | G126: =J126*K126*L126+1200 -> 4560 | I126: general labour plus 20 yard skip | J126: 140 | K126: 6 | L126: 4
B128: Allow to remove 2nd floor structure and entirety including joists, noggins, floor boards and fixing etc. and dispose off site. | C128: =G128 -> 3600 | E128: 80 | F128: m2 | G128: =J128*K128*L128+800 -> 3600 | I128: general labour plus 20 yard skip | J128: 140 | K128: 5 | L128: 4
B130: Allow to complete work in stages and agree with C.A onsite. | C130: Inc
A133: 4.2 | B133: Party Wall
B134: Where shown on drawings, contractor to provide all materials, labour and expertise to extend the party wall in reclaimed London stock brickwork in a Flemish bond (Header/ Stretcher Bond) and bonded with sand and cement mortar to form new walls as shown on contract drawings. All mortar to be Class 4 mortar to BS 5628-3:2001. | C134: =E134*G134 -> 3770 | E134: 26 | F134: m2 | G134: 145
B136: Brick colour to match sound existing and samples of bricks to be provided to CA for approval prior to installation. Point brickwork with matching joints to that of the existing building. | C136: Inc
B138: For supply of bricks allow Prime Cost sum of £1500 per 1000 for supply only. | C138: Inc
B140: Allow to form appropriate movement joints within walls where new walls exceed 6.0m in length. Exact locations to be confirmed onsite and at returns where possible. | C140: Inc
B142: At roof level, provide all materials, labour and expertise to supply and fix 30mm x 5mm galvanised metal straps at maximum 2m centres fixed back to a minimum of 3 joists and built in to brickwork. | C142: Inc
B144: Prepare the new parapet wall above new roof covering, dubbing out as necessary to receive new contractor supplied and installed DPC. Thereafter, contractor to supply and install new twice struck concrete coping stone with drip grooves, bedded on sand cement mortar and thereafter point all joints with polysulphide mastic leaving all sound on completion. | C144: =E144*G144 -> 2772 | E144: 21 | F144: m | G144: 132
A146: 4.3 | B146: New 2nd floor structure
B147: In location shown on drawings, contractor to reduce the 2nd floor structure in height to provide sufficient head room in 2nd floor space and provide all materials, labour and expertise to supply and fix 50 x 220 x C24 soft wood floor joists at 400 centres with timber solid noggins at supports at 1.8 m centres in locations shown on general arrangement drawings. | C147: =M147+AM147 -> 3030 | I147: carp | J147: 180 | K147: 2 | L147: 3 | M147: =L147*K147*J147 -> 1080 | X147: c24 50x220 | Y147: length | Z147: 40 | AA147: 40 | AB147: hangers | AC147: no | AD147: 4 | AE147: 50 | AF147: fixings | AG147: 1 | AH147: 150 | AM147: =SUM(Z147*AA147)+(AD147*AE147)+AH147 -> 1950
B149: Floor joists to be supported on Simpson Strong Tie, or similar approved, galvanised steel joist hangers or built into external walls. | C149: Inc
B151: Leave ready to receive floating floor and ceiling treatment as detailed below. | C151: Inc
A153: 4.4 | B153: New rafters
B154: Where walls plates have been removed, Contractor to supply and install 50 x 175 x C24 tanalised softwood wall plate to the face of the new external brickwork wall as illustrated on drawings. Fix wall plate with resin anchored M12 140mm bolts at staggered 300mm centres. | C154: 760
B156: Where shown on drawings, contractor to supply and install 50 x 125 C16 tanalised rafters at 400mm centres with birdsmouth seatings at supports. Allow to supply and fix solid strutting at mid span. Make allowance for Dormer window and Velux room lights with double trimmers and rafters around. | C156: =M156+AM156 -> 3420 | I156: carp | J156: 180 | K156: 3.5 | L156: 3 | M156: =L156*K156*J156 -> 1890 | X156: c16 50x125 | Y156: length | Z156: 30 | AA156: 40 | AB156: hangers | AC156: no | AD156: 4 | AE156: 50 | AF156: fixings | AG156: 1 | AH156: 130 | AM156: =SUM(Z156*AA156)+(AD156*AE156)+AH156 -> 1530
A158: 4.5 | B158: Insulation
B159: Contractor to supply and install 100mm Celotex foil faced PIR thermal insulation board between rafters, supported on clips to maintain a 25mm air gap above the breather membrane. All boards to be butt fixed and with no gaps. | C159: =M159+AM159 -> 4250 | I159: carp | J159: 180 | K159: 2.5 | L159: 3 | M159: =L159*K159*J159 -> 1350 | X159: pir board | Y159: sheets | Z159: 80 | AA159: 35 | AB159: clips | AD159: 100 | AM159: =Z159*AA159+AD159 -> 2900
B161: Contractor to supply and install Celotex 50mm insulated plasterboard to the underside of the rafters. Leave ready for plaster skim coat and decoration. | C161: =M161+AM161 -> 3420 | I161: carp | J161: 180 | K161: 2 | L161: 3 | M161: =L161*K161*J161 -> 1080 | X161: 50mm insulated plasterboard | Y161: sheets | Z161: 70 | AA161: 32 | AB161: fixings | AD161: 100 | AM161: =Z161*AA161+AD161 -> 2340
...

Sheet Prelims
B1: Preliminaries:
C2: 95 Malvern Road | G2: 12 | H2: weeks
B4: Preliminary Items | D4: Rate/ Week | E4: % | F4: No. Req'd | G4: Weeks/No | H4: Total / Week
B6: 1. Staff
B7: 1.1 | C7: Construction Manager (Visiting) | D7: 1900
B8: 1.2 | C8: Non-Working Project Managers (Project Based) | D8: 1600 | E8: 1 | F8: 1 | G8: =G2 -> 12 | H8: =D8*E8*F8*G8 -> 19200
B9: 1.3 | C9: Surveyor (Visiting) | D9: 1350 | E9: 0.05 | F9: 1 | G9: =G2 -> 12 | H9: =D9*E9*F9*G9 -> 810
B10: 1.4 | C10: Procurement / Ordering Materials | D10: INCLUDED
B11: 1.5 | C11: Part Working Foremen (Project Based) - Setting out/ labour supervision/ deliveries etc | D11: 1250 | E11: 0 | F11: 1 | G11: =G2 -> 12 | H11: =D11*E11*F11*G11 -> 0
B12: 1.6 | C12: Store & Logistics (Project Based) | D12: EXCLUDED
B13: 1.7 | C13: Programmer (Off Site) | D13: 1300 | E13: 0 | F13: 1 | G13: =G2 -> 12 | H13: =D13*E13*F13*G13 -> 0
B14: 1.8 | C14: Design Manager (Off Site) | D14: EXCLUDED
B15: 1.9 | C15: Engineering Assistant | D15: EXCLUDED
B16: 1.1 | C16: Chain Boy | D16: EXCLUDED
B17: 1.11 | C17: Labour to load out (Horizontal) | D17: 840 | E17: 0 | F17: 1 | G17: =G2 -> 12 | H17: =D17*E17*F17*G17 -> 0
B18: 1.12 | C18: First Aiders Allowance | D18: 40 | H18: =D18 -> 40
B19: 1.13 | C19: H & S Consultant | D19: 800 | E19: 0.2 | F19: 1 | G19: =G2 -> 12 | H19: =D19*E19*F19*G19 -> 1920
B20: 1.14 | C20: Van + Fuel | D20: 120 | E20: 1 | F20: 1 | G20: =G2 -> 12 | H20: =D20*E20*F20*G20 -> 1440
B21: 1.15 | C21: Engineering | D21: 1300 | E21: 0 | F21: 1 | G21: =G20 -> 12 | H21: =D21*E21*F21*G21 -> 0
B22: 1.16 | C22: Banksman / Slinger (Part Time) | D22: EXCLUDED
B23: 1.17 | C23: Admin office/ Surveying Assistance | D23: EXCLUDED
H24: =SUM(H7:H23) -> 23410
B26: 2. Accomodation
B27: 2.1 | C27: Site Office / s | D27: 55 | E27: 1 | F27: 1 | G27: =G19 -> 12 | H27: =D27*E27*F27*G27 -> 660
B28: 2.2 | C28: Storage Container /s | D28: 30 | E28: 1 | F28: 1 | G28: =G19 -> 12 | H28: =D28*E28*F28*G28 -> 360
B29: 2.3 | C29: Computer /s & Consumables | D29: 22 | E29: 0 | F29: 1 | G29: =G19 -> 12 | H29: =D29*E29*F29*G29 -> 0
B30: 2.4 | C30: Phone | D30: 20 | E30: 1 | F30: 1 | G30: =G19 -> 12 | H30: =D30*E30*F30*G30 -> 240
B31: 2.5 | C31: Internet | D31: INCLUDED
B32: 2.6 | C32: Portaloos | D32: 22 | E32: 1 | F32: 1 | G32: =G19 -> 12 | H32: =D32*E32*F32*G32 -> 264
B33: 2.7 | C33: Generator and fuel | D33: 79 | E33: 0 | F33: 1 | G33: =G19 -> 12 | H33: =D33*E33*F33*G33 -> 0
B34: 2.8 | C34: Set up & Dismantle | D34: INCLUDED
H35: =SUM(H27:H34) -> 1524
B37: 3. Plant
B38: 3.1 | C38: Forklift, driver, diesel & bowser | D38: EXCLUDED
B39: 3.2 | C39: Whacker plate | D39: 40 | E39: 0 | F39: 2 | G39: =G33 -> 12 | H39: =D39*E39*F39*G39 -> 0
B40: 3.3 | C40: Consumables | D40: 25 | E40: 1 | F40: 1 | G40: =G33 -> 12 | H40: =D40*E40*F40*G40 -> 300
B41: 3.4 | C41: Mixer | D41: 35 | E41: 1 | F41: 1 | G41: =G33 -> 12 | H41: =D41*E41*F41*G41 -> 420
B42: 3.5 | C42: Wheelbarrows | D42: 18 | E42: 1 | F42: 3 | G42: 1 | H42: =D42*E42*F42*G42 -> 54
B43: 3.6 | C43: Barriers/Heras with feet (batch of 15 panels) | D43: 95 | E43: 1 | F43: 1 | G43: =G33 -> 12 | H43: =D43*E43*F43*G43 -> 1140
B44: 3.7 | C44: Drills | D44: 15 | E44: 1 | F44: 1 | G44: =G33 -> 12 | H44: =D44*E44*F44*G44 -> 180
B45: 3.8 | C45: Grinders | D45: 15 | E45: 1 | F45: 1 | G45: =G33 -> 12 | H45: =D45*E45*F45*G45 -> 180
B46: 3.9 | C46: Breakers | D46: 35 | E46: 0 | F46: 1 | G46: =G33 -> 12 | H46: =D46*E46*F46*G46 -> 0
B47: 3.1 | C47: Leads | D47: INCLUDED
B48: 3.11 | C48: Task Lights | D48: INCLUDED
B49: 3.12 | C49: Engineers levels | D49: INCLUDED
B50: 3.13 | C50: Traffic signage | D50: 16 | E50: 0 | F50: 1 | G50: =G33 -> 12 | H50: =D50*E50*F50*G50 -> 0
B51: 3.14 | C51: Generator and fuel | D51: 79 | E51: 0 | F51: 1 | G51: =G50 -> 12 | H51: =D51*E51*F51*G51 -> 0
B52: 3.15 | C52: Radios | D52: 12 | E52: 0 | F52: 1 | G52: =G33 -> 12 | H52: =D52*E52*F52*G52 -> 0
H53: =SUM(H38:H52) -> 2274
B55: 4. Access
B56: 4.1 | C56: Scaffold | D56: EXCLUDED
B57: 4.2 | C57: Safestand | D57: EXCLUDED
B58: 4.3 | C58: Podium Steps | D58: EXCLUDED
B59: 4.4 | C59: Scissors Lift / Cherry Picker | D59: EXCLUDED
B60: 4.5 | C60: Mobile Towers | D60: EXCLUDED | H60: 500
H61: =SUM(H56:H60) -> 500
B63: 5. Rubbish
B64: 5.1 | C64: Skips | D64: EXCLUDED
B65: 5.2 | C65: Trolley bins | D65: EXCLUDED
B66: 5.3 | C66: Labour to clear rubbish and clean | D66: EXCLUDED
H67: =SUM(H64:H66) -> 0
B69: 6. Other
B70: 6.1 | C70: Protection Generally | D70: 60 | E70: 0 | F70: 1 | G70: =G52 -> 12 | H70: =D70*E70*F70*G70 -> 0
B71: 6.2 | C71: Insurance for works | D71: INCLUDED
B72: 6.3 | C72: PPE | D72: 25 | E72: 1 | F72: 1 | G72: =G52 -> 12 | H72: =D72*E72*F72*G72 -> 300
B73: 6.4 | C73: H&S file | D73: 75 | E73: 1 | F73: 1 | G73: =G52 -> 12 | H73: =D73*E73*F73*G73 -> 900
B74: 6.5 | C74: Mock Ups ( As built sample) | D74: EXCLUDED
B75: 6.6 | C75: Final Clean | D75: INCLUDED
B76: 6.7 | C76: QA | D76: 35 | E76: 0 | F76: 1 | G76: =G52 -> 12 | H76: =D76*E76*F76*G76 -> 0
B77: 6.8 | C77: O & M Manuals | D77: 20 | E77: 1 | F77: 1 | G77: =G52 -> 12 | H77: =D77*E77*F77*G77 -> 240
B78: 6.9 | C78: Engineering / Temp Works Design | D78: EXCLUDED
B79: 6.1 | C79: Drawing Production | D79: EXCLUDED
B80: 6.11 | C80: Liasing with residents - leaflets, signage, calls | D80: 15 | E80: 1 | F80: 1 | G80: =G52 -> 12 | H80: =D80*E80*F80*G80 -> 180
B81: 6.12 | C81: Signage | D81: 15 | E81: 1 | F81: 1 | G81: =G52 -> 12 | H81: =D81*E81*F81*G81 -> 180
B82: 6.13 | C82: Van and fuel | D82: 140 | E82: 0 | F82: 1 | G82: =G52 -> 12 | H82: =D82*E82*F82*G82 -> 0
B83: 6.14 | C83: 10% Performance Bond | D83: EXCLUDED
B84: 6.15 | C84: Survey Cost | D84: EXCLUDED
H85: =SUM(H70:H84) -> 1800
G87: Total | H87: =SUM(H24+H35+H53+H61+H67+H85) -> 29508

Sheet SoRs
A1: Project description | C1: Schedule of Daywork Rates | F1: Revision | G1: 1
F2: Date | G2: =NOW() -> 43621.606
A4: BoQ | B4: Supplier | C4: Description | D4: Quant | E4: unit | F4: Rate | G4: Add/omit
A5: A | C5: B | D5: C | E5: D | F5: E | G5: F
U6: =T6*Q5 -> 0
C7: Daywork Rates
G8: =F8*D8 -> 0
C9: Manager/Supervisor - £350 | D9: 350 | G9: =F9*D9 -> 0
C10: Quantity Surveyor - £320 | D10: 320
C11: Planner - £310 | D11: 310
C12: Tiler - £250 | D12: 250 | G12: =F12*D12 -> 0
C13: Carpenter - £270 | D13: 270 | G13: =F13*D13 -> 0
C14: Labourer - £140 | D14: 140 | G14: =F14*D14 -> 0
C15: Brickworker - £260 | D15: 260
C16: Groundworker - £260 | D16: 260
C17: Machine Driver - £280 | D17: 280
C19: Non Productive working:
C20: Saturday 8am to 5pm 150% | G20: =F20*D20 -> 0
C21: Sunday 8am to 4pm 200%
C22: Note: Labour rates exclude Supervision
C24: Plant cost + 15% | G24: =F24*D24 -> 0
C25: Subcontractors cost + 20% | G25: =F25*D25 -> 0
C26: Materials cost + 15%
G27: =F27*D27 -> 0
G30: =SUM(G6:G27) -> 0
A31: Clarifications | G31: =IF(D31>-0.01,D31*F31,"Omission") -> 0
G32: =IF(D32>-0.01,D32*F32,"Omission") -> 0
A35: Programme Implications | G35: =IF(D35>-0.01,D35*F35,"Omission") -> 0
G38: =IF(D38>-0.01,D38*F38,"Omission") -> 0
C39: Sub Total measured works | G39: =SUM(G30) -> 0
C44: Total Value £ | G44: =SUM(G39:G43) -> 0

Sheet Measure
C1: length | D1: width | E1: high | F1: floor | G1: walls | H1: ceiling | I1: perimeter | J1: doors | K1: windows | L1: size | M1: fans | N1: bath suite | O1: boiler | P1: kitchen | Q1: rads | R1: CU | T1: steelwork | U1: length | W1: pads | X1: Splice/Connc
B2: upper ground floor | C2: m | D2: m | E2: m | F2: m2 | G2: m2 | H2: m2 | I2: lm | T2: kg/m
B3: bed 1 | C3: 3.56 | D3: 4.585 | E3: 3.5 | F3: =C3*D3 -> 16.3226 | G3: =SUM(C3+D3+C3+D3)*E3 -> 57.015 | H3: =F3 -> 16.3226 | I3: =SUM(E3+F3+E3+F3) -> 39.6452 | J3: 1 | K3: 1 | Q3: 1 | T3: 97 | U3: 6.2 | V3: =T3*U3 -> 601.4 | W3: 2 | X3: 1
B4: bath 1 | C4: 2 | D4: 1.67 | E4: 3.5 | F4: =C4*D4 -> 3.34 | G4: =SUM(C4+D4+C4+D4)*E4 -> 25.69 | H4: =F4 -> 3.34 | I4: =SUM(E4+F4+E4+F4) -> 13.68 | J4: 1 | M4: 1 | N4: 1 | Q4: 1 | T4: 32 | U4: 6 | V4: =T4*U4 -> 192 | W4: 1 | X4: 2
B5: bed 2 | C5: 5 | D5: 2 | E5: 3.5 | F5: =C5*D5 -> 10 | G5: =SUM(C5+D5+C5+D5)*E5 -> 49 | H5: =F5 -> 10 | I5: =SUM(E5+F5+E5+F5) -> 27 | J5: 1 | K5: 1 | Q5: 1 | T5: 13 | U5: 6 | V5: =T5*U5 -> 78 | W5: 1 | X5: 2
B6: bath 2 | C6: 2 | D6: 1.7 | E6: 3.5 | F6: =C6*D6 -> 3.4 | G6: =SUM(C6+D6+C6+D6)*E6 -> 25.9 | H6: =F6 -> 3.4 | I6: =SUM(E6+F6+E6+F6) -> 13.8 | J6: 1 | M6: 1 | N6: 1 | O6: 1 | P6: 1 | Q6: 1
B7: kitchen/lounge | C7: 4.6 | D7: 4.585 | E7: 3.5 | F7: =C7*D7 -> 21.091 | G7: =SUM(C7+D7+C7+D7)*E7 -> 64.295 | H7: =F7 -> 21.091 | I7: =SUM(E7+F7+E7+F7) -> 49.182 | J7: 1 | K7: 1 | M7: 1 | Q7: 1 | R7: 1
B8: hallway | C8: 2 | D8: 2.5 | E8: 3.5 | F8: =C8*D8 -> 5 | G8: =SUM(C8+D8+C8+D8)*E8 -> 31.5 | H8: =F8 -> 5 | I8: =SUM(E8+F8+E8+F8) -> 17 | J8: 1 | Q8: 1
B9: main hallway | C9: 2 | D9: 4 | E9: 3.5 | F9: =C9*D9 -> 8 | G9: =SUM(C9+D9+C9+D9)*E9 -> 42 | H9: =F9 -> 8 | I9: =SUM(E9+F9+E9+F9) -> 23 | J9: 2 | Q9: 1
B11: first floor
B12: bed 1 | C12: 3.445 | D12: 4.585 | E12: 2.6 | F12: =C12*D12 -> 15.795325 | G12: =SUM(C12+D12+C12+D12)*E12 -> 41.756 | H12: =F12 -> 15.795325 | I12: =SUM(E12+F12+E12+F12) -> 36.79065 | J12: 1 | K12: 1 | Q12: 1 | S12: t1 | T12: 73 | U12: 6.2 | V12: =T12*U12 -> 452.6 | W12: 15 | X12: 1
B13: bath 1 | C13: 1.915 | D13: 1.95 | E13: 2.6 | F13: =C13*D13 -> 3.73425 | G13: =SUM(C13+D13+C13+D13)*E13 -> 20.098 | H13: =F13 -> 3.73425 | I13: =SUM(E13+F13+E13+F13) -> 12.6685 | J13: 1 | K13: 1 | M13: 1 | Q13: 1 | S13: t2 | T13: 23 | U13: 3 | V13: =T13*U13 -> 69
B14: bed 2 | C14: 2.62 | D14: 3.585 | E14: 2.6 | F14: =C14*D14 -> 9.3927 | G14: =SUM(C14+D14+C14+D14)*E14 -> 32.266 | H14: =F14 -> 9.3927 | I14: =SUM(E14+F14+E14+F14) -> 23.9854 | J14: 1 | K14: 1 | Q14: 1 | S14: t3 | T14: 23 | U14: 2 | V14: =T14*U14 -> 46
B15: bath 2 | C15: 2.021 | D15: 1.95 | E15: 2.6 | F15: =C15*D15 -> 3.94095 | G15: =SUM(C15+D15+C15+D15)*E15 -> 20.6492 | H15: =F15 -> 3.94095 | I15: =SUM(E15+F15+E15+F15) -> 13.0819 | J15: 1 | M15: 1 | Q15: 1 | S15: t4 | T15: 16 | U15: 4 | V15: =T15*U15 -> 64
B16: kitchen/lounge | C16: 4.455 | D16: 4 | E16: 2.6 | F16: =C16*D16 -> 17.82 | G16: =SUM(C16+D16+C16+D16)*E16 -> 43.966 | H16: =F16 -> 17.82 | I16: =SUM(E16+F16+E16+F16) -> 40.84 | J16: 1 | K16: 1 | M16: 1 | O16: 1 | P16: 1 | Q16: 1 | R16: 1 | S16: t5 | T16: 16 | U16: 5 | V16: =T16*U16 -> 80 | X16: 1
B17: hallway | C17: 1 | D17: 2.6 | E17: 2.6 | F17: =C17*D17 -> 2.6 | G17: =SUM(C17+D17+C17+D17)*E17 -> 18.72 | H17: =F17 -> 2.6 | I17: =SUM(E17+F17+E17+F17) -> 10.4 | J17: 1 | Q17: 1 | S17: t6 | T17: 23 | U17: 6.2 | V17: =T17*U17 -> 142.6 | X17: 1
B18: cupboard | C18: 0.6 | D18: 1.2 | E18: 2.6 | F18: =C18*D18 -> 0.72 | G18: =SUM(C18+D18+C18+D18)*E18 -> 9.36 | H18: =F18 -> 0.72 | I18: =SUM(E18+F18+E18+F18) -> 6.64 | J18: 3 | Q18: 1 | S18: t7 | T18: 23 | U18: 6.2 | V18: =T18*U18 -> 142.6 | X18: 1
B19: stairwell | C19: 2 | D19: 4 | E19: 2.6 | F19: =C19*D19 -> 8 | G19: =SUM(C19+D19+C19+D19)*E19 -> 31.2 | H19: =F19 -> 8 | I19: =SUM(E19+F19+E19+F19) -> 21.2 | J19: 1 | K19: 1 | Q19: 1 | S19: b1 | T19: 73 | U19: 5.2 | V19: =T19*U19 -> 379.6 | X19: 1
S20: b2 | T20: 71 | U20: 6.5 | V20: =T20*U20 -> 461.5 | X20: 1
B21: second floor | S21: l1 | T21: 46 | U21: 2.5 | V21: =T21*U21 -> 115
B22: bed | C22: 3.885 | D22: 4.2 | E22: 2.4 | F22: =C22*D22 -> 16.317 | G22: =SUM(C22+D22+C22+D22)*E22 -> 38.808 | H22: =F22 -> 16.317 | I22: =SUM(E22+F22+E22+F22) -> 37.434 | J22: 1 | K22: 1 | Q22: 1
B23: bath | C23: 1.7 | D23: 2 | E23: 2.4 | F23: =C23*D23 -> 3.4 | G23: =SUM(C23+D23+C23+D23)*E23 -> 17.76 | H23: =F23 -> 3.4 | I23: =SUM(E23+F23+E23+F23) -> 11.6 | J23: 1 | M23: 1 | N23: 1 | Q23: 1 | S23: rb1 | T23: 46 | U23: 5 | V23: =T23*U23 -> 230 | W23: 5 | X23: 1
B24: lounge | C24: 4.655 | D24: 3.1 | E24: 2.4 | F24: =C24*D24 -> 14.4305 | G24: =SUM(C24+D24+C24+D24)*E24 -> 37.224 | H24: =F24 -> 14.4305 | I24: =SUM(E24+F24+E24+F24) -> 33.661 | J24: 1 | K24: 1 | Q24: 1 | S24: rb2 | T24: 46 | U24: 5 | V24: =T24*U24 -> 230 | X24: 1
B25: kitchen | C25: 4.8 | D25: 1.83 | E25: 2.4 | F25: =C25*D25 -> 8.784 | G25: =SUM(C25+D25+C25+D25)*E25 -> 31.824 | H25: =F25 -> 8.784 | I25: =SUM(E25+F25+E25+F25) -> 22.368 | J25: 1 | K25: 1 | M25: 1 | O25: 1 | P25: 1 | Q25: 1 | R25: 1 | S25: rb3 | T25: 46 | U25: 5 | V25: =T25*U25 -> 230 | X25: 1
B26: hallway | C26: 2 | D26: 3 | E26: 2.4 | F26: =C26*D26 -> 6 | G26: =SUM(C26+D26+C26+D26)*E26 -> 24 | H26: =F26 -> 6 | I26: =SUM(E26+F26+E26+F26) -> 16.8 | J26: 1 | Q26: 1 | S26: t1 | T26: 46 | U26: 8 | V26: =T26*U26 -> 368 | X26: 1
B27: stairwell | C27: 4 | D27: 2 | E27: 2.4 | F27: =C27*D27 -> 8 | G27: =SUM(C27+D27+C27+D27)*E27 -> 28.8 | H27: =F27 -> 8 | I27: =SUM(E27+F27+E27+F27) -> 20.8 | J27: 1 | K27: 1 | Q27: 1 | S27: t2 | T27: 23 | U27: 2 | V27: =T27*U27 -> 46
S28: posts | T28: 46 | U28: 10 | V28: =T28*U28 -> 460
F29: =SUM(F3:F28) -> 186.08832 | G29: =SUM(G3:G28) -> 691.8312 | H29: =SUM(H3:H28) -> 186.08832 | I29: =SUM(I3:I28) -> 491.57665 | J29: =SUM(J3:J28) -> 24 | K29: =SUM(K3:K28) -> 12 | L29: =SUM(L3:L28) -> 0 | M29: =SUM(M3:M28) -> 8 | ... R29: =SUM(R3:R28) -> 3 | V29: =SUM(V3:V28) -> 4388.3 | W29: =SUM(W3:W28) -> 24 | X29: =SUM(X3:X28) -> 15
V30: =V29/900 -> 4.8758889 | W30: T
I31: linings | J31: 80
J32: =J29*J31 -> 1920 | S32: Steel | T32: 1420 | U32: =V30*T32 -> 6923.7622
S33: pads | T33: 190 | U33: =W29*T33 -> 4560
I34: FD30 | J34: 280 | S34: splice | T34: 140 | U34: =X29*T34 -> 2100
J35: =J29*J34 -> 6720 | S35: Props | T35: 250 | U35: =T35 -> 250
F36: 650 | G36: 4 | H36: =F36*G36 -> 2600 | S36: Genie | T36: 400 | U36: =T36 -> 400
F37: 60 | G37: 100 | H37: =F37*G37 -> 6000 | U37: =SUM(U32:U36) -> 14233.762
F38: 60 | G38: 24 | H38: =F38*G38 -> 1440
F39: 130 | H39: =F39*G39 -> 0
F40: 60 | G40: 5 | H40: =F40*G40 -> 300
F41: 55 | G41: 24 | H41: =F41*G41 -> 1320
F42: 75 | G42: 100 | H42: =F42*G42 -> 7500
F43: 75 | G43: 8 | H43: =F43*G43 -> 600
F44: 95 | G44: 12 | H44: =F44*G44 -> 1140
F45: 250 | H45: =F45*G45 -> 0
F46: 90 | G46: 10 | H46: =F46*G46 -> 900
F47: 90 | G47: 10 | H47: =F47*G47 -> 900
F48: 150 | G48: 6 | H48: =F48*G48 -> 900
F49: 120 | G49: 8 | H49: =F49*G49 -> 960
F50: 200 | G50: 3 | H50: =F50*G50 -> 600
H51: =SUM(H36:H50) -> 25160
